hfmc/__init__.py
hfmc/hfmc.py
hfmc/client/__init__.py
hfmc/client/http_request.py
hfmc/client/model_cmd.py
hfmc/client/model_controller.py
hfmc/client/peer_cmd.py
hfmc/client/peer_controller.py
hfmc/client/uninstall_cmd.py
hfmc/common/__init__.py
hfmc/common/api_settings.py
hfmc/common/context.py
hfmc/common/etag.py
hfmc/common/hf_wrapper.py
hfmc/common/peer.py
hfmc/common/repo_files.py
hfmc/config/__init__.py
hfmc/config/conf_cmd.py
hfmc/config/config_manager.py
hfmc/config/hfmc_config.py
hfmc/daemon/__init__.py
hfmc/daemon/daemon_cmd.py
hfmc/daemon/manager.py
hfmc/daemon/prober.py
hfmc/daemon/server.py
hfmc/daemon/handlers/__init__.py
hfmc/daemon/handlers/daemon_handler.py
hfmc/daemon/handlers/fetch_handler.py
hfmc/daemon/handlers/peer_handler.py
hfmc/utils/__init__.py
hfmc/utils/args.py
hfmc/utils/auth_cmd.py
hfmc/utils/logging.py
hfmc/utils/yaml.py
hfmc-0.1.10.dist-info/METADATA
hfmc-0.1.10.dist-info/WHEEL
hfmc-0.1.10.dist-info/entry_points.txt
hfmc-0.1.10.dist-info/licenses/LICENSE
hfmc-0.1.10.dist-info/RECORD
